{
  "current": {
    "sec_spacing": 55,
    "sttlstl": "2",
    "ttlelw": 50,
    "heading_weight": "600",
    "section_heading_1_size": 24,
    "section_heading_1_lh": 1.4,
    "hdelem": "#ffc6ac",
    "section_heading_2_size": 16,
    "enable_site_animation": false,
    "wishlist_page": "wishlist",
    "en_searchwords": true,
    "favicon": "shopify:\/\/shop_images\/favicon.png",
    "favicon_retina": "shopify:\/\/shop_images\/favicon-152.png",
    "hm_keywords": "Best Shopify Theme, Fashion theme, Electronics",
    "hm_author": "Sanjay Khunt",
    "breadcrumb_cl": false,
    "free_ship": "free-shipping",
    "free_ship_msg": "Spent $ more for free shipping",
    "got_free_ship": "You have got <b>FREE SHIPPING<\/b>",
    "terms_checkbox": false,
    "enable_birthdate": true,
    "body_font": "futura_n4",
    "header_font": "futura_n4",
    "font3": "futura_n4",
    "type_base_size": 14,
    "type_header_base_size_lh": 1,
    "type_header_base_size": 30,
    "type_header_base_size_2": 26,
    "type_header_base_size_3": 20,
    "type_header_base_size_4": 15,
    "type_header_base_size_5": 14,
    "type_header_base_size_6": 13,
    "type_header_letter_space": 2,
    "color_text_field": "#fff",
    "field_bd": "#dddddd",
    "btnwt": "500",
    "btn_style": "flat",
    "btn_fs": 12,
    "btn_ls": 1,
    "color_button": "#111",
    "btn1_bd": "rgba(0,0,0,0)",
    "color_button_text_hov": "#fff",
    "color_button_hov": "#fe877b",
    "btn1_bd_hover": "rgba(0,0,0,0)",
    "color_small_button_text": "#fff",
    "color_small_button": "#fe877b",
    "btn2_bd": "#fe877b",
    "btn2_bd_hove": "#111",
    "solid_btn_3": "#23a3bb",
    "solid_btn_3_b": "#23a3bb",
    "link_btn_txt": "#f17171",
    "navigation_font_size": 14,
    "navigation_txt_case": "capitalize",
    "nav_h": 55,
    "navbarbdr": "rgba(0,0,0,0)",
    "navbar": "#fff",
    "navbar_link": "#000",
    "navbar_link_hv": "#f77575",
    "nav_link_lbl": "#fff",
    "nav_link_lbl1": "#06b608",
    "nav_link_lbl3": "#f48920",
    "nav_link_lbl5": "#ff0000",
    "nav_mm_link_hv": "#f77575",
    "nav_mm_title_case": "none",
    "nav_dd_link": "#444",
    "nav_dd_link_bghv": "#fafafa",
    "nav_dd_divider": "#eeeeee",
    "subnav_color_shade": "darken",
    "h_weight": "600",
    "sidebar_links_hv": "#f77575",
    "footer_top_bdr": "rgba(0,0,0,0)",
    "footer_top_bg": "#111",
    "footer_title": "#fff",
    "top_footer_text": "#fff",
    "icon_colors": "#fff",
    "newsletter_input": "#fff",
    "newsletter_btn": "#000",
    "footer_bottom_bg": "#111",
    "footer_bottom_text": "#f9f9f9",
    "footer_border": "#111",
    "ttl-font": 22,
    "mob_browser": "#000",
    "scroll_icon_colors": "#f77575",
    "text_link": "#444",
    "text_link_hv": "#f77575",
    "color_borders": "#eeeeee",
    "announcement": false,
    "announcement_mb": true,
    "announcement_txt": "<b>BLAZING FAST !<\/b> PURCHASE THIS INCREDIBLE THEME NOW <b> FOR THE SUCCESS OF YOUR BUSINESS !<\/b>",
    "announcement_link": "shopify:\/\/collections\/all",
    "annouance_bg": "#121212",
    "annouance_fs": 11,
    "topbar": true,
    "topbar_fullwidth": true,
    "leftTxt": "<a href=\"tel:4400111044%20833\"><i class=\"at at-phone-l\"><\/i> +440 0(111) 044 833<\/a>\n<a href=\"mailto:sales@yourstorename.com\"><i class=\"at at-envelope-l\"><\/i> sales@yourstorename.com<\/a>",
    "centerTxt": "Increase & Maximize sales with AVONE.",
    "rightTxt": "Follow Us: [social-icons]",
    "top_header_clr": "#111",
    "main_header_fullwidth": true,
    "logo": "shopify:\/\/shop_images\/footer-logo.png",
    "logo_width": "100",
    "header_height": "80",
    "mobile_header_height": "50",
    "sticky_logo_width": "100",
    "sticky_header_height": "60",
    "header_ico": "#030505",
    "icon_size": 16,
    "my_account_icn": "at at-user-al",
    "drawer_bdr": "#eeeeee",
    "icon_style": "sq-bag",
    "cart_count_clr": "#030505",
    "home_classic": true,
    "icon_text_clr": "#030505",
    "giftwrap": true,
    "gift_product": "gift-wrapping",
    "coupon": true,
    "primg_ratio": "130",
    "primg_size": "cover",
    "color_type": "vrimage",
    "vr_bg_position": "50% 50%",
    "color_size": "medium",
    "swatch_rad": 14,
    "acti_swatch_bdr_clr": "#fe877b",
    "prttlcl": "#111111",
    "prttlcla": "#e55151",
    "pr_title_size": 14,
    "pr_font_w": "500",
    "color_sale_text": "#f77575",
    "enable_quickshop": true,
    "prbox_btnbg": "#000",
    "prbox_btn_icoh": "#fff",
    "prbox_btnbgh": "#fe877b",
    "btn_mobiles": true,
    "grid_countdown_text": "#000",
    "grid_countdown_border": "#fff",
    "gcountdown_bgopt": 0.7,
    "prbox_bdr": "rgba(0,0,0,0)",
    "product_latyout": "style3",
    "icw": 60,
    "enable_lightbox": false,
    "thumbnail_pos": "bottom",
    "askaboutproduct": true,
    "shippingpopup": false,
    "shippingpage": "delivary-and-returns",
    "sizechart_page": "size-chart",
    "sharing_lbl": "Share:",
    "swbdr": 22,
    "ac_swatch_bg": "#111",
    "ac_swatch_txt": "#fff",
    "spr_navigation": true,
    "dynamic_btn": true,
    "sticky_cart": false,
    "cart_text": "#f5f5f5",
    "cart_qty_bdr": "#535353",
    "cart_btn_text": "#fff",
    "cart_btn": "#e34848",
    "currency_opt": "script",
    "currency_title": "Currency",
    "show_language": true,
    "langOpt": "2",
    "language_title": "Language",
    "languages": "language",
    "show_notification": true,
    "notify_collection": "hot-collection",
    "notify_msg": "Someone liked and Bought",
    "notify_delay": "5000",
    "mailChimp_url": "",
    "newsltr-style": "style1",
    "newsletter_img": "shopify:\/\/shop_images\/newsletter-horizontal.png",
    "newsletter_popup_title": "Join Our Mailing List",
    "show_closetrext": true,
    "newsltr_close": "#dddddd",
    "show_social_icons": true,
    "newsletter_social_icn": "#121212",
    "social_twitter_link": "https:\/\/twitter.com\/adornthemes",
    "social_facebook_link": "https:\/\/www.facebook.com\/adornthemes\/",
    "social_pinterest_link": "https:\/\/in.pinterest.com\/adornthemes\/",
    "social_instagram_link": "https:\/\/www.instagram.com\/adornthemes\/",
    "checkout_logo_image": "shopify:\/\/shop_images\/footer-logo.png",
    "checkout_logo_size": "small",
    "checkout_button_color": "#121212",
    "logosvg": "<svg version=\"1.1\" id=\"Layer_1\" xmlns=\"http:\/\/www.w3.org\/2000\/svg\" x=\"0px\" y=\"0px\" width=\"400px\" height=\"82px\" viewbox=\"0 0 400 82\" enable-background=\"new 0 0 400 82\" xmlns:xlink=\"http:\/\/www.w3.org\/1999\/xlink\" xml:space=\"preserve\">\n<text transform=\"matrix(1 0 0 1 69.7529 415.1504)\"><tspan x=\"0\" y=\"0\" font-family=\"'Poppins-ExtraBold'\" font-size=\"72\" letter-spacing=\"-3\">A<\/tspan><tspan x=\"50.544\" y=\"0\" font-family=\"'Poppins-ExtraBold'\" font-size=\"72\" letter-spacing=\"1\">V<\/tspan><tspan x=\"105.983\" y=\"0\" font-family=\"'Poppins-ExtraBold'\" font-size=\"72\" letter-spacing=\"3\">ONE<\/tspan><\/text>\n<g>\n\t<path d=\"M54.766,67.227H27.107L22.81,80.229H0L28.54,2.543h25.014l28.43,77.687h-22.92L54.766,67.227z M49.367,50.918\n\t\tl-8.375-25.345l-8.485,25.345H49.367z\"><\/path>\n\t<path d=\"M100.386,2.212l17.631,56.199l17.521-56.199h23.03l-26.667,78.018h-27.878L77.356,2.212H100.386z\"><\/path>\n\t<path d=\"M225.401,6.124c6.062,3.416,10.835,8.173,14.326,14.27c3.488,6.099,5.234,12.968,5.234,20.607\n\t\tc0,7.641-1.764,14.509-5.291,20.605c-3.527,6.099-8.318,10.854-14.381,14.27c-6.059,3.417-12.725,5.125-19.998,5.125\n\t\tc-7.272,0-13.959-1.708-20.057-5.125c-6.099-3.416-10.908-8.171-14.435-14.27c-3.527-6.097-5.288-12.965-5.288-20.605\n\t\tc0-7.64,1.761-14.509,5.288-20.607c3.527-6.097,8.336-10.854,14.435-14.27c6.098-3.416,12.784-5.125,20.057-5.125\n\t\tC212.637,0.999,219.342,2.708,225.401,6.124z M192.289,26.399c-3.159,3.564-4.741,8.43-4.741,14.602\n\t\tc0,6.023,1.582,10.836,4.741,14.435c3.157,3.601,7.491,5.399,13.003,5.399c5.435,0,9.733-1.799,12.893-5.399\n\t\tc3.156-3.599,4.738-8.411,4.738-14.435c0-6.172-1.563-11.037-4.684-14.602c-3.125-3.563-7.438-5.345-12.947-5.345\n\t\tC199.78,21.055,195.446,22.837,192.289,26.399z\"><\/path>\n\t<path d=\"M332.231,80.229h-21.707l-28.648-43.526v43.526h-21.711V2.322h21.711l28.648,44.077V2.322h21.707V80.229z\"><\/path>\n\t<path d=\"M371.462,19.513v12.893h25.232v16.419h-25.232v14.104H400v17.301h-50.249V2.212H400v17.301H371.462z\"><\/path>\n<\/g>\n<\/svg>",
    "show_free_ship": true,
    "show_estimate_ship": false,
    "slideshow_text_1": 20,
    "slideshow_text_2": 45,
    "slideshow_text_2_lh": 1.2,
    "slideshow_text_3": 19,
    "slideshow_text_3_lh": 1.3,
    "color_slideshow_image_overlay": "rgba(0,0,0,0)",
    "image_slideshow_overlay_opacity": 0,
    "display_overlay_mb": false,
    "tab_font_size": 13,
    "pr_tab_txt": "#000",
    "pr_tab_txt_ac": "#fff",
    "pr_tab_brd": "rgba(0,0,0,0)",
    "pr_tab_brd_ac": "rgba(0,0,0,0)",
    "pr_tab_bg": "rgba(0,0,0,0)",
    "pr_tab_ac_bg": "#000",
    "text_size_heading": 25,
    "text_size_content": 18,
    "pbanner-title": 30,
    "pbanner-des": 16,
    "quote-title": 24,
    "video_ttl": 30,
    "cl_bnr_title": 20,
    "cl_bnr_des": 16,
    "color_style": "rounded_rectangle",
    "show_saleoff": false,
    "show_taxlbl": false,
    "spr_vendor": true,
    "enable_payment_button": true,
    "pickup_show": false,
    "countdown_lbl": "Hurry up! Sales End In:",
    "countdown_text": "#000",
    "countdown_text_bg": "#f8f8f8",
    "countdown_border": "#dddddd",
    "sw_color_type": "color",
    "sw_color_size": "small",
    "sw_color_style": "rounded",
    "product_qunt_bg": "#000",
    "fake_visitors": true,
    "visitors_time": 5,
    "store_ft1": "",
    "store_ft2": "",
    "store_ft3": "",
    "Prod_name_font_size": 24,
    "prod_font_weight": "600",
    "prod_title_transform": "capitalize",
    "Prod_price_font_size": 22,
    "prod_price_font_weight": "600",
    "sprice": "#e34848",
    "checkout_btn_bg": "#fe877b",
    "tab_align": "center",
    "prTab_ft": 13,
    "pr_tabs_bg_act": "#fe877b",
    "pr_tabs_txt_act": "#fff",
    "dis_border": false,
    "pr_tabs_bdr": "#eeeeee",
    "pr_tabs_bdr_act": "#dddddd",
    "logo_height": "40",
    "hero_text_size_heading": 22,
    "hero_text_size_content": 14,
    "color_image_overlay_text": "#000",
    "text_bg_opacity": 0.7,
    "Products_countdown_text_bg_opacity1": 65,
    "sections": {
      "navigation": {
        "type": "navigation",
        "blocks": {
          "1545200462991": {
            "type": "megamenu1",
            "settings": {
              "title": "Home",
              "url": "#",
              "newtab": false,
              "mm_linklist": "demos",
              "mmcolumns": 4,
              "imgcall": "bottom",
              "columnWidth": 50,
              "mmimgcolumns": 1,
              "imageTtl1": "",
              "imageurl": "",
              "megamenu2_image": "shopify:\/\/shop_images\/freeship.jpg",
              "imageTtl2": "",
              "Image2url": "shopify:\/\/collections\/women",
              "imageTtl3": "",
              "Image3url": "#",
              "imageTtl4": "",
              "Image4url": "",
              "show_bdr": true,
              "img_rad": 0,
              "custom_size": true,
              "mm_size": "800",
              "mm_align": "left",
              "box_sized": false
            }
          },
          "1560070247268": {
            "type": "megamenu1",
            "settings": {
              "title": "Shop",
              "url": "#",
              "newtab": false,
              "mm_linklist": "shop-1",
              "mmcolumns": 2,
              "imgcall": "right",
              "columnWidth": 31,
              "mmimgcolumns": 1,
              "megamenu1_image": "shopify:\/\/shop_images\/WOMXN.jpg",
              "imageTtl1": "New Arrival",
              "imageurl": "shopify:\/\/collections\/women-fashion",
              "megamenu2_image": "shopify:\/\/shop_images\/MECV.jpg",
              "imageTtl2": "Shop Men",
              "Image2url": "shopify:\/\/collections\/men",
              "imageTtl3": "",
              "Image3url": "",
              "imageTtl4": "",
              "Image4url": "",
              "show_bdr": true,
              "img_rad": 0,
              "custom_size": true,
              "mm_size": "700",
              "mm_align": "left",
              "box_sized": false
            }
          },
          "1560145007901": {
            "type": "megamenu1",
            "settings": {
              "title": "Features",
              "url": "#",
              "newtab": false,
              "mm_linklist": "features",
              "mmcolumns": 5,
              "imgcall": "right",
              "columnWidth": 50,
              "mmimgcolumns": 2,
              "imageTtl1": "",
              "imageurl": "",
              "imageTtl2": "",
              "Image2url": "",
              "imageTtl3": "",
              "Image3url": "",
              "imageTtl4": "",
              "Image4url": "",
              "show_bdr": true,
              "img_rad": 0,
              "custom_size": true,
              "mm_size": "900",
              "mm_align": "left",
              "box_sized": false
            }
          },
          "1559988240897": {
            "type": "dropdown",
            "settings": {
              "title": "Lookbook",
              "url": "",
              "mm_linklist": "lookbook"
            }
          },
          "1580487002618": {
            "type": "megamenu4",
            "settings": {
              "title": "Pages",
              "url": "#",
              "newtab": false,
              "mm_linklist": "pages",
              "mmcolumns": 2,
              "mm4_bg": "shopify:\/\/shop_images\/MMbgwomen.jpg",
              "mm4_img_position": "right",
              "mm4_space": "50%",
              "custom_size": true,
              "mm_size": "600",
              "mm_align": "center",
              "box_sized": false
            }
          },
          "1559992848977": {
            "type": "dropdown",
            "settings": {
              "title": "Blog",
              "url": "#",
              "mm_linklist": "blog"
            }
          },
          "69db0513-e385-4089-b441-2af258c033ee": {
            "type": "dropdown",
            "settings": {
              "title": "Buy Now!",
              "url": "https:\/\/1.envato.market\/KdyYx",
              "mm_linklist": "buy-now"
            }
          }
        },
        "block_order": [
          "1545200462991",
          "1560070247268",
          "1560145007901",
          "1559988240897",
          "1580487002618",
          "1559992848977",
          "69db0513-e385-4089-b441-2af258c033ee"
        ],
        "settings": {
          "menuarrow": false,
          "menuAlign": "left",
          "spnav": false,
          "mbmenu": "main-menu",
          "nm_label1": "New",
          "nm_label2": "Sale",
          "nm_label3": "Hot",
          "nm_label4": "Popular",
          "nm_label5": "Trending"
        }
      },
      "footer": {
        "type": "footer",
        "blocks": {
          "1558602521885": {
            "type": "contact",
            "settings": {
              "title": "Contact Us",
              "logo-width": 150,
              "address": "55 Gallaxy Enque,<br>2568 steet, 23568 NY",
              "phone": "(440) 000 000 0000",
              "email": "sales@yousite.com",
              "show_icons": true,
              "show_socials": false,
              "socials_ttl": "Stay Connected",
              "width": "wd25-md"
            }
          },
          "1558599099773": {
            "type": "menu",
            "settings": {
              "title": "Informations",
              "menulinks": "information",
              "width": "wd25-md"
            }
          },
          "1558599110848": {
            "type": "menu",
            "settings": {
              "title": "Quick Shop",
              "menulinks": "quick-shop",
              "width": "wd25-md"
            }
          },
          "1558602799954": {
            "type": "socialicons",
            "settings": {
              "title": "Stay Connected",
              "width": "wd25-md"
            }
          }
        },
        "block_order": [
          "1558602521885",
          "1558599099773",
          "1558599110848",
          "1558602799954"
        ],
        "settings": {
          "section_width": false,
          "copyright_text": "© 2024 Avone. All Rights Reserved. Ecommerce Software by Shopify",
          "show_designby": true,
          "show_payment": false,
          "payment_img_width": "350",
          "snow_effect": false,
          "snow_style": "style2"
        }
      },
      "custom-colors": {
        "type": "custom-colors",
        "blocks": {
          "1888fda2-fecc-4309-8739-4092a6f9dedf": {
            "type": "Color",
            "settings": {
              "title1": "Red",
              "color1": "#f05454",
              "title2": "Emerald",
              "color2": "#00646c",
              "title3": "White\/Black",
              "color3": "",
              "image3": "shopify:\/\/shop_images\/White-Black_501ba5c3-86d5-4f37-99ea-a6671b3c4ea3.jpg",
              "title4": "Sage",
              "color4": "#8da29a",
              "title5": "Olive Green",
              "color5": "#bab86c",
              "title6": "Blue",
              "color6": "#77bff2",
              "title7": "Green",
              "color7": "#37b767",
              "title8": "Camel",
              "color8": "#df974d",
              "title9": "Black\/Pink",
              "color9": "",
              "image9": "shopify:\/\/shop_images\/pink-black.jpg",
              "title10": "Black\/Grey",
              "color10": "",
              "image10": "shopify:\/\/shop_images\/grey-black.jpg",
              "title11": "Blue\/Red",
              "color11": "",
              "image11": "shopify:\/\/shop_images\/blue-red.jpg",
              "title12": "",
              "color12": "",
              "title13": "",
              "color13": "",
              "title14": "",
              "color14": "",
              "title15": "",
              "color15": ""
            }
          }
        },
        "block_order": [
          "1888fda2-fecc-4309-8739-4092a6f9dedf"
        ],
        "settings": {
          "custom_colors": true
        }
      },
      "exit-product-popup": {
        "type": "exit-product-popup",
        "settings": {
          "popup": true,
          "title": "Can't find what you're looking for?",
          "subtitle": "We have some handpicked items for you!",
          "collection": "women-fashion",
          "secondary_image": true,
          "show_vendor": false,
          "prlist_btn_show": false,
          "btn_mobiles": false,
          "show_view_all": "",
          "show_color_swatch": true,
          "color_type": "color",
          "vr_bg_position": "50% 0",
          "color_size": "small",
          "prbox_style": "style1",
          "grid": 4,
          "tablet-grid": 3,
          "mobile-grid": 2,
          "rows": "5",
          "autoplay": false,
          "autoplay_speed": 5,
          "ex-index": true,
          "ex-product": false,
          "ex-collection": false,
          "ex-article": false,
          "ex-blog": false,
          "ex-cart": false,
          "ex-page": false
        }
      },
      "mobile-toolbar": {
        "type": "mobile-toolbar",
        "settings": {
          "showmt": true,
          "hdtxt": false,
          "fsicon": 16,
          "fs": 12,
          "fw": "600",
          "cl": "#333",
          "bg": "#fff",
          "bgg": ""
        }
      }
    },
    "content_for_index": [

    ]
  },
  "presets": {
  }
}